[
  {
  "year": 2008,
  "avg": 63,
  "high": 68,
  "low": 58
  },
  {
  "year": 2009,
  "avg": 62,
  "high": 70,
  "low": 53
  },
  {
  "year": 2010,
  "avg": 67,
  "high": 74,
  "low": 59
  },
  {
  "year": 2011,
  "avg": 60,
  "high": 64,
  "low": 55
  },
  {
  "year": 2012,
  "avg": 62,
  "high": 69,
  "low": 54
  },
  {
  "year": 2013,
  "avg": 61,
  "high": 69,
  "low": 53
  },
  {
  "year": 2014,
  "avg": 70,
  "high": 81,
  "low": 59
  },
  {
  "year": 2015,
  "avg": 69,
  "high": 79,
  "low": 59
  },
  {
  "year": 2016,
  "avg": 64,
  "high": 73,
  "low": 54
  },
  {
  "year": 2017,
  "avg": 70,
  "high": 85,
  "low": 55
  },
  {
  "year": 2018,
  "avg": 62,
  "high": 69,
  "low": 55
  }
]
